anaties/__init__.py
anaties/helpers.py
anaties/plots.py
anaties/signals.py
anaties/stats.py
anaties/workspace.py
anaties-0.1.4.6.dist-info/LICENSE.md
anaties-0.1.4.6.dist-info/METADATA
anaties-0.1.4.6.dist-info/WHEEL
anaties-0.1.4.6.dist-info/top_level.txt
anaties-0.1.4.6.dist-info/RECORD
