Metadata-Version: 2.1
Name: anaties
Version: 0.1.4.6
Summary: Common analysis utilities
Home-page: https://github.com/EricThomson/anaties
Author: Eric Thomson
Author-email: thomson.eric@gmail.com
License: MIT
Platform: UNKNOWN
License-File: LICENSE.md
Requires-Dist: numpy
Requires-Dist: matplotlib
Requires-Dist: scipy
